Encoder_project/basic/rtl/cores/DISPLAY/SPI/SPI.v
//------------------------------------------------------------mòdulo principal -------------------------------------------------------//

module SPI(reset,clk,init,data_tx,MISO,done,data_rx,spi_clk,MOSI);

    input reset;
	input clk;             
	input init;
    input [7:0]data_tx;
    input MISO;

    output done;
    output [7:0]data_rx;
    output spi_clk;
    output MOSI;

    wire w_sh;
    wire w_reset;
    wire w_load;
    wire w_send;
    wire w_x;

control_SPI control0(.reset(reset),.clk(clk),.init(init),.x(w_x),.spi_clk(spi_clk),.dn(done),.sh(w_sh),.ld(w_load),.sd(w_send));
spiclk spiclk0(.shift(w_sh),.send(w_send),.load(w_load),.spi_clk(spi_clk),.x(w_x));
data data0(.load(w_load),.shift(w_sh),.send(w_send),.data_tx(data_tx),.MISO(MISO),.MOSI(MOSI),.data_rx(data_rx));

endmodule

//----------------------------------------------modulo de manipulaciòn del registro data ---------------------------------------------//

module data(load,shift,send,data_tx,MISO,MOSI,data_rx);
   input load;
   input shift;
   input send;
   input [7:0]data_tx;
   input MISO;
   
   output reg[7:0]data_rx;
   output reg MOSI;
   
initial begin
    data_rx = 0;
    MOSI = 0;
end

always @(*)begin
    if (load) data_rx = data_tx;
    else if (shift) data_rx = {MISO,data_rx[7:1]};
    else if (send) MOSI = data_rx[0];
end

endmodule

//----------------------------------------------------------modulo señal de reloj y finalizaciòn ----------------------------------------------------//

module spiclk(shift,send,load,spi_clk,x);
    input shift;
    input send;
    input load;
    
    output reg spi_clk;
    output x;

reg temp;
reg [3:0] bit_cnt;
parameter size_pack = 8;
assign x = temp;

initial begin 
    spi_clk = 0;
    temp = 0;
    bit_cnt = 0;
end

always @(*)begin
    if (load) begin 
        bit_cnt = 0;
        temp = 0;
    end
    else begin
        if (bit_cnt != size_pack) begin
            if (send) spi_clk = 1;
            else if (shift) begin
                spi_clk = 0;
                bit_cnt = bit_cnt + 1;
            end
        end
        else if (send) temp = 1;
    end
end

endmodule


//------------------------------------------------------------mòdulo control ---------------------------------------------------------//

module control_SPI(reset,clk,init,x,spi_clk,dn,sh,ld,sd);
	input reset;
	input clk;             
	input init;
    input x;
    input spi_clk;

	output reg dn; 
    output reg sh;
    output reg ld;
    output reg sd;     
    			
parameter START = 3'b000, LOAD = 3'b001, SEND = 3'b010,SHIFT = 3'b011, SPI_CLK = 3'b100, DONE = 3'b101;
reg [2:0] state;

parameter medio_periodo = 5;
reg [14:0] count;

initial begin 
    dn = 0;
    sh = 0;
    sd = 0;
    ld = 0;
    state = 0;
    count = 0;
end 
always @(posedge clk) begin
    if (reset) begin 
        state = START;
    end
    else begin 
        case (state)
            START:

                if (init) state = LOAD;
                else state = START;
                
            LOAD:begin
            
                count = 0;
                state = SPI_CLK;
            end    
            SPI_CLK:
                
                if (x) begin
                state = DONE;
                end 
                else begin
                    if(count != medio_periodo && count != 2*medio_periodo)   begin
                        count = count + 1;
                        state = SPI_CLK;
                    end else if (count == medio_periodo) begin
                        state = SEND;
                        count = count + 1;
                    end else begin
                        state = SHIFT;
                        count = 0;
                    end
                end
            SEND:
                state = SPI_CLK;
            SHIFT:
                state = SPI_CLK;
            DONE:
                state = START;

            default:
                state = START;
        endcase
   end
end

always @(*) begin
    case (state)
        START: begin     
            sh = 0;
            ld = 0;
            sd = 0;
        end

        LOAD: begin
            dn = 0;
            sh = 0;
            ld = 1;
            sd = 0;
        end
        SPI_CLK: begin 
            dn = 0;
            sh = 0;
            ld = 0;
            sd = 0;
        end
        SEND: begin
            dn = 0;
            sh = 0;
            ld = 0;
            sd = 1;
        end
        
        SHIFT: begin 
            dn = 0;
            sh = 1;
            ld = 0;
            sd = 0;
        end     
        DONE: begin
            dn = 1;
            sh = 0;
            ld = 0;
            sd = 0;
        end
    endcase
end

`ifdef BENCH
reg [8*40:1] state_name;
always @(*) begin
  case(state)
    START    : state_name = "START";
    LOAD   : state_name = "LOAD";
    SEND    : state_name = "SEND";
    SPI_CLK   : state_name = "SPI_CLK";
    SHIFT    : state_name = "SHIFT";
    DONE    : state_name = "DONE";
  endcase
end
`endif
endmodule

Encoder_project/basic/rtl/cores/DISPLAY/SPI/SPI_TB.v
`timescale 1ns / 1ps
`define SIMULATION
module SPI_TB;
   reg  clk;
   reg  reset;
   reg  init;
   reg  [7:0] data_tx;
   reg  MISO;

   wire done;
   wire spi_clk;
   wire MOSI;
   wire [7:0] data_rx;

   SPI uut (
      .clk(clk), 
      .reset(reset), 
      .init(init), 
      .data_tx(data_tx),
      .MISO(MISO),
      .done(done),
      .spi_clk(spi_clk),
      .MOSI(MOSI),
      .data_rx(data_rx)
   );

   parameter PERIOD = 20;
   initial begin  
      clk = 0; reset = 0; init = 0; data_tx = 0; MISO = 0;
   end
  
   initial         clk <= 0;
   always #(PERIOD/2) clk <= ~clk;

   initial begin 
   
        reset = 1;
        init = 0;
        data_tx = 8'h00;
        #(PERIOD);
        reset = 0;

  

        data_tx = 8'hAA;
        init = 1;
        #(PERIOD);
        init = 0;
        wait(done == 1);
 


        #(PERIOD);
        data_tx = 8'hAA;
        init = 1;
        #(2*PERIOD);
        init = 0;
        wait(done == 1);
    

   end
	 

   initial begin: TEST_CASE
     $dumpfile("SPI_TB.vcd");
     $dumpvars(-1, SPI_TB);
     #(PERIOD*250) $finish;
   end

endmodule

Encoder_project/basic/rtl/cores/DISPLAY/SPI/SPI_TB.vcd
$date
	Tue Jul  8 22:16:37 2025
$end
$version
	Icarus Verilog
$end
$timescale
	1ps
$end
$scope module SPI_TB $end
$var wire 1 ! spi_clk $end
$var wire 1 " done $end
$var wire 8 # data_rx [7:0] $end
$var wire 1 $ MOSI $end
$var parameter 32 % PERIOD $end
$var reg 1 & MISO $end
$var reg 1 ' clk $end
$var reg 8 ( data_tx [7:0] $end
$var reg 1 ) init $end
$var reg 1 * reset $end
$scope module uut $end
$var wire 1 & MISO $end
$var wire 1 ' clk $end
$var wire 8 + data_tx [7:0] $end
$var wire 1 ) init $end
$var wire 1 * reset $end
$var wire 1 , w_x $end
$var wire 1 - w_sh $end
$var wire 1 . w_send $end
$var wire 1 / w_load $end
$var wire 1 ! spi_clk $end
$var wire 1 " done $end
$var wire 8 0 data_rx [7:0] $end
$var wire 1 $ MOSI $end
$scope module control0 $end
$var wire 1 ' clk $end
$var wire 1 ) init $end
$var wire 1 * reset $end
$var wire 1 , x $end
$var wire 1 ! spi_clk $end
$var parameter 3 1 DONE $end
$var parameter 3 2 LOAD $end
$var parameter 3 3 SEND $end
$var parameter 3 4 SHIFT $end
$var parameter 3 5 SPI_CLK $end
$var parameter 3 6 START $end
$var parameter 32 7 medio_periodo $end
$var reg 15 8 count [14:0] $end
$var reg 1 " dn $end
$var reg 1 / ld $end
$var reg 1 . sd $end
$var reg 1 - sh $end
$var reg 3 9 state [2:0] $end
$var reg 320 : state_name [320:1] $end
$upscope $end
$scope module data0 $end
$var wire 1 & MISO $end
$var wire 8 ; data_tx [7:0] $end
$var wire 1 / load $end
$var wire 1 . send $end
$var wire 1 - shift $end
$var reg 1 $ MOSI $end
$var reg 8 < data_rx [7:0] $end
$upscope $end
$scope module spiclk0 $end
$var wire 1 / load $end
$var wire 1 . send $end
$var wire 1 - shift $end
$var wire 1 , x $end
$var parameter 32 = size_pack $end
$var reg 4 > bit_cnt [3:0] $end
$var reg 1 ! spi_clk $end
$var reg 1 ? temp $end
$upscope $end
$upscope $end
$scope begin TEST_CASE $end
$upscope $end
$upscope $end
$enddefinitions $end
$comment Show the parameter values. $end
$dumpall
b1000 =
b101 7
b0 6
b100 5
b11 4
b10 3
b1 2
b101 1
b10100 %
$end
#0
$dumpvars
0?
b0 >
b0 <
b0 ;
b101001101010100010000010101001001010100 :
b0 9
b0 8
b0 0
0/
0.
0-
0,
b0 +
1*
0)
b0 (
0'
0&
0$
b0 #
0"
0!
$end
#10000
1'
#20000
0'
1)
b10101010 (
b10101010 +
b10101010 ;
0*
#30000
b10101010 #
b10101010 0
b10101010 <
1/
b1001100010011110100000101000100 :
b1 9
1'
#40000
0'
0)
#50000
b1010011010100000100100101011111010000110100110001001011 :
0/
b100 9
1'
#60000
0'
#70000
b1 8
1'
#80000
0'
#90000
b10 8
1'
#100000
0'
#110000
b11 8
1'
#120000
0'
#130000
b100 8
1'
#140000
0'
#150000
b101 8
1'
#160000
0'
#170000
1!
1.
b1010011010001010100111001000100 :
b110 8
b10 9
1'
#180000
0'
#190000
b1010011010100000100100101011111010000110100110001001011 :
0.
b100 9
1'
#200000
0'
#210000
b111 8
1'
#220000
0'
#230000
b1000 8
1'
#240000
0'
#250000
b1001 8
1'
#260000
0'
#270000
b1010 8
1'
#280000
0'
#290000
b1010101 #
b1010101 0
b1010101 <
b1 >
0!
1-
b101001101001000010010010100011001010100 :
b0 8
b11 9
1'
#300000
0'
#310000
b1010011010100000100100101011111010000110100110001001011 :
0-
b100 9
1'
#320000
0'
#330000
b1 8
1'
#340000
0'
#350000
b10 8
1'
#360000
0'
#370000
b11 8
1'
#380000
0'
#390000
b100 8
1'
#400000
0'
#410000
b101 8
1'
#420000
0'
#430000
1$
1!
1.
b1010011010001010100111001000100 :
b110 8
b10 9
1'
#440000
0'
#450000
b1010011010100000100100101011111010000110100110001001011 :
0.
b100 9
1'
#460000
0'
#470000
b111 8
1'
#480000
0'
#490000
b1000 8
1'
#500000
0'
#510000
b1001 8
1'
#520000
0'
#530000
b1010 8
1'
#540000
0'
#550000
b101010 #
b101010 0
b101010 <
b10 >
0!
1-
b101001101001000010010010100011001010100 :
b0 8
b11 9
1'
#560000
0'
#570000
b1010011010100000100100101011111010000110100110001001011 :
0-
b100 9
1'
#580000
0'
#590000
b1 8
1'
#600000
0'
#610000
b10 8
1'
#620000
0'
#630000
b11 8
1'
#640000
0'
#650000
b100 8
1'
#660000
0'
#670000
b101 8
1'
#680000
0'
#690000
0$
1!
1.
b1010011010001010100111001000100 :
b110 8
b10 9
1'
#700000
0'
#710000
b1010011010100000100100101011111010000110100110001001011 :
0.
b100 9
1'
#720000
0'
#730000
b111 8
1'
#740000
0'
#750000
b1000 8
1'
#760000
0'
#770000
b1001 8
1'
#780000
0'
#790000
b1010 8
1'
#800000
0'
#810000
b10101 #
b10101 0
b10101 <
b11 >
0!
1-
b101001101001000010010010100011001010100 :
b0 8
b11 9
1'
#820000
0'
#830000
b1010011010100000100100101011111010000110100110001001011 :
0-
b100 9
1'
#840000
0'
#850000
b1 8
1'
#860000
0'
#870000
b10 8
1'
#880000
0'
#890000
b11 8
1'
#900000
0'
#910000
b100 8
1'
#920000
0'
#930000
b101 8
1'
#940000
0'
#950000
1$
1!
1.
b1010011010001010100111001000100 :
b110 8
b10 9
1'
#960000
0'
#970000
b1010011010100000100100101011111010000110100110001001011 :
0.
b100 9
1'
#980000
0'
#990000
b111 8
1'
#1000000
0'
#1010000
b1000 8
1'
#1020000
0'
#1030000
b1001 8
1'
#1040000
0'
#1050000
b1010 8
1'
#1060000
0'
#1070000
b1010 #
b1010 0
b1010 <
b100 >
0!
1-
b101001101001000010010010100011001010100 :
b0 8
b11 9
1'
#1080000
0'
#1090000
b1010011010100000100100101011111010000110100110001001011 :
0-
b100 9
1'
#1100000
0'
#1110000
b1 8
1'
#1120000
0'
#1130000
b10 8
1'
#1140000
0'
#1150000
b11 8
1'
#1160000
0'
#1170000
b100 8
1'
#1180000
0'
#1190000
b101 8
1'
#1200000
0'
#1210000
0$
1!
1.
b1010011010001010100111001000100 :
b110 8
b10 9
1'
#1220000
0'
#1230000
b1010011010100000100100101011111010000110100110001001011 :
0.
b100 9
1'
#1240000
0'
#1250000
b111 8
1'
#1260000
0'
#1270000
b1000 8
1'
#1280000
0'
#1290000
b1001 8
1'
#1300000
0'
#1310000
b1010 8
1'
#1320000
0'
#1330000
b101 #
b101 0
b101 <
b101 >
0!
1-
b101001101001000010010010100011001010100 :
b0 8
b11 9
1'
#1340000
0'
#1350000
b1010011010100000100100101011111010000110100110001001011 :
0-
b100 9
1'
#1360000
0'
#1370000
b1 8
1'
#1380000
0'
#1390000
b10 8
1'
#1400000
0'
#1410000
b11 8
1'
#1420000
0'
#1430000
b100 8
1'
#1440000
0'
#1450000
b101 8
1'
#1460000
0'
#1470000
1$
1!
1.
b1010011010001010100111001000100 :
b110 8
b10 9
1'
#1480000
0'
#1490000
b1010011010100000100100101011111010000110100110001001011 :
0.
b100 9
1'
#1500000
0'
#1510000
b111 8
1'
#1520000
0'
#1530000
b1000 8
1'
#1540000
0'
#1550000
b1001 8
1'
#1560000
0'
#1570000
b1010 8
1'
#1580000
0'
#1590000
b10 #
b10 0
b10 <
b110 >
0!
1-
b101001101001000010010010100011001010100 :
b0 8
b11 9
1'
#1600000
0'
#1610000
b1010011010100000100100101011111010000110100110001001011 :
0-
b100 9
1'
#1620000
0'
#1630000
b1 8
1'
#1640000
0'
#1650000
b10 8
1'
#1660000
0'
#1670000
b11 8
1'
#1680000
0'
#1690000
b100 8
1'
#1700000
0'
#1710000
b101 8
1'
#1720000
0'
#1730000
0$
1!
1.
b1010011010001010100111001000100 :
b110 8
b10 9
1'
#1740000
0'
#1750000
b1010011010100000100100101011111010000110100110001001011 :
0.
b100 9
1'
#1760000
0'
#1770000
b111 8
1'
#1780000
0'
#1790000
b1000 8
1'
#1800000
0'
#1810000
b1001 8
1'
#1820000
0'
#1830000
b1010 8
1'
#1840000
0'
#1850000
b1 #
b1 0
b1 <
b111 >
0!
1-
b101001101001000010010010100011001010100 :
b0 8
b11 9
1'
#1860000
0'
#1870000
b1010011010100000100100101011111010000110100110001001011 :
0-
b100 9
1'
#1880000
0'
#1890000
b1 8
1'
#1900000
0'
#1910000
b10 8
1'
#1920000
0'
#1930000
b11 8
1'
#1940000
0'
#1950000
b100 8
1'
#1960000
0'
#1970000
b101 8
1'
#1980000
0'
#1990000
1$
1!
1.
b1010011010001010100111001000100 :
b110 8
b10 9
1'
#2000000
0'
#2010000
b1010011010100000100100101011111010000110100110001001011 :
0.
b100 9
1'
#2020000
0'
#2030000
b111 8
1'
#2040000
0'
#2050000
b1000 8
1'
#2060000
0'
#2070000
b1001 8
1'
#2080000
0'
#2090000
b1010 8
1'
#2100000
0'
#2110000
b0 #
b0 0
b0 <
b1000 >
0!
1-
b101001101001000010010010100011001010100 :
b0 8
b11 9
1'
#2120000
0'
#2130000
b1010011010100000100100101011111010000110100110001001011 :
0-
b100 9
1'
#2140000
0'
#2150000
b1 8
1'
#2160000
0'
#2170000
b10 8
1'
#2180000
0'
#2190000
b11 8
1'
#2200000
0'
#2210000
b100 8
1'
#2220000
0'
#2230000
b101 8
1'
#2240000
0'
#2250000
0$
1,
1?
1.
b1010011010001010100111001000100 :
b110 8
b10 9
1'
#2260000
0'
#2270000
b1010011010100000100100101011111010000110100110001001011 :
0.
b100 9
1'
#2280000
0'
#2290000
1"
b1000100010011110100111001000101 :
b101 9
1'
#2300000
0'
#2310000
b101001101010100010000010101001001010100 :
b0 9
1'
1)
#2320000
0'
#2330000
b10101010 #
b10101010 0
b10101010 <
0,
0?
b0 >
1/
0"
b1001100010011110100000101000100 :
b1 9
1'
#2340000
0'
#2350000
b1010011010100000100100101011111010000110100110001001011 :
0/
b100 9
b0 8
1'
0)
#2360000
0'
#2370000
b1 8
1'
#2380000
0'
#2390000
b10 8
1'
#2400000
0'
#2410000
b11 8
1'
#2420000
0'
#2430000
b100 8
1'
#2440000
0'
#2450000
b101 8
1'
#2460000
0'
#2470000
1!
1.
b1010011010001010100111001000100 :
b110 8
b10 9
1'
#2480000
0'
#2490000
b1010011010100000100100101011111010000110100110001001011 :
0.
b100 9
1'
#2500000
0'
#2510000
b111 8
1'
#2520000
0'
#2530000
b1000 8
1'
#2540000
0'
#2550000
b1001 8
1'
#2560000
0'
#2570000
b1010 8
1'
#2580000
0'
#2590000
b1010101 #
b1010101 0
b1010101 <
b1 >
0!
1-
b101001101001000010010010100011001010100 :
b0 8
b11 9
1'
#2600000
0'
#2610000
b1010011010100000100100101011111010000110100110001001011 :
0-
b100 9
1'
#2620000
0'
#2630000
b1 8
1'
#2640000
0'
#2650000
b10 8
1'
#2660000
0'
#2670000
b11 8
1'
#2680000
0'
#2690000
b100 8
1'
#2700000
0'
#2710000
b101 8
1'
#2720000
0'
#2730000
1$
1!
1.
b1010011010001010100111001000100 :
b110 8
b10 9
1'
#2740000
0'
#2750000
b1010011010100000100100101011111010000110100110001001011 :
0.
b100 9
1'
#2760000
0'
#2770000
b111 8
1'
#2780000
0'
#2790000
b1000 8
1'
#2800000
0'
#2810000
b1001 8
1'
#2820000
0'
#2830000
b1010 8
1'
#2840000
0'
#2850000
b101010 #
b101010 0
b101010 <
b10 >
0!
1-
b101001101001000010010010100011001010100 :
b0 8
b11 9
1'
#2860000
0'
#2870000
b1010011010100000100100101011111010000110100110001001011 :
0-
b100 9
1'
#2880000
0'
#2890000
b1 8
1'
#2900000
0'
#2910000
b10 8
1'
#2920000
0'
#2930000
b11 8
1'
#2940000
0'
#2950000
b100 8
1'
#2960000
0'
#2970000
b101 8
1'
#2980000
0'
#2990000
0$
1!
1.
b1010011010001010100111001000100 :
b110 8
b10 9
1'
#3000000
0'
#3010000
b1010011010100000100100101011111010000110100110001001011 :
0.
b100 9
1'
#3020000
0'
#3030000
b111 8
1'
#3040000
0'
#3050000
b1000 8
1'
#3060000
0'
#3070000
b1001 8
1'
#3080000
0'
#3090000
b1010 8
1'
#3100000
0'
#3110000
b10101 #
b10101 0
b10101 <
b11 >
0!
1-
b101001101001000010010010100011001010100 :
b0 8
b11 9
1'
#3120000
0'
#3130000
b1010011010100000100100101011111010000110100110001001011 :
0-
b100 9
1'
#3140000
0'
#3150000
b1 8
1'
#3160000
0'
#3170000
b10 8
1'
#3180000
0'
#3190000
b11 8
1'
#3200000
0'
#3210000
b100 8
1'
#3220000
0'
#3230000
b101 8
1'
#3240000
0'
#3250000
1$
1!
1.
b1010011010001010100111001000100 :
b110 8
b10 9
1'
#3260000
0'
#3270000
b1010011010100000100100101011111010000110100110001001011 :
0.
b100 9
1'
#3280000
0'
#3290000
b111 8
1'
#3300000
0'
#3310000
b1000 8
1'
#3320000
0'
#3330000
b1001 8
1'
#3340000
0'
#3350000
b1010 8
1'
#3360000
0'
#3370000
b1010 #
b1010 0
b1010 <
b100 >
0!
1-
b101001101001000010010010100011001010100 :
b0 8
b11 9
1'
#3380000
0'
#3390000
b1010011010100000100100101011111010000110100110001001011 :
0-
b100 9
1'
#3400000
0'
#3410000
b1 8
1'
#3420000
0'
#3430000
b10 8
1'
#3440000
0'
#3450000
b11 8
1'
#3460000
0'
#3470000
b100 8
1'
#3480000
0'
#3490000
b101 8
1'
#3500000
0'
#3510000
0$
1!
1.
b1010011010001010100111001000100 :
b110 8
b10 9
1'
#3520000
0'
#3530000
b1010011010100000100100101011111010000110100110001001011 :
0.
b100 9
1'
#3540000
0'
#3550000
b111 8
1'
#3560000
0'
#3570000
b1000 8
1'
#3580000
0'
#3590000
b1001 8
1'
#3600000
0'
#3610000
b1010 8
1'
#3620000
0'
#3630000
b101 #
b101 0
b101 <
b101 >
0!
1-
b101001101001000010010010100011001010100 :
b0 8
b11 9
1'
#3640000
0'
#3650000
b1010011010100000100100101011111010000110100110001001011 :
0-
b100 9
1'
#3660000
0'
#3670000
b1 8
1'
#3680000
0'
#3690000
b10 8
1'
#3700000
0'
#3710000
b11 8
1'
#3720000
0'
#3730000
b100 8
1'
#3740000
0'
#3750000
b101 8
1'
#3760000
0'
#3770000
1$
1!
1.
b1010011010001010100111001000100 :
b110 8
b10 9
1'
#3780000
0'
#3790000
b1010011010100000100100101011111010000110100110001001011 :
0.
b100 9
1'
#3800000
0'
#3810000
b111 8
1'
#3820000
0'
#3830000
b1000 8
1'
#3840000
0'
#3850000
b1001 8
1'
#3860000
0'
#3870000
b1010 8
1'
#3880000
0'
#3890000
b10 #
b10 0
b10 <
b110 >
0!
1-
b101001101001000010010010100011001010100 :
b0 8
b11 9
1'
#3900000
0'
#3910000
b1010011010100000100100101011111010000110100110001001011 :
0-
b100 9
1'
#3920000
0'
#3930000
b1 8
1'
#3940000
0'
#3950000
b10 8
1'
#3960000
0'
#3970000
b11 8
1'
#3980000
0'
#3990000
b100 8
1'
#4000000
0'
#4010000
b101 8
1'
#4020000
0'
#4030000
0$
1!
1.
b1010011010001010100111001000100 :
b110 8
b10 9
1'
#4040000
0'
#4050000
b1010011010100000100100101011111010000110100110001001011 :
0.
b100 9
1'
#4060000
0'
#4070000
b111 8
1'
#4080000
0'
#4090000
b1000 8
1'
#4100000
0'
#4110000
b1001 8
1'
#4120000
0'
#4130000
b1010 8
1'
#4140000
0'
#4150000
b1 #
b1 0
b1 <
b111 >
0!
1-
b101001101001000010010010100011001010100 :
b0 8
b11 9
1'
#4160000
0'
#4170000
b1010011010100000100100101011111010000110100110001001011 :
0-
b100 9
1'
#4180000
0'
#4190000
b1 8
1'
#4200000
0'
#4210000
b10 8
1'
#4220000
0'
#4230000
b11 8
1'
#4240000
0'
#4250000
b100 8
1'
#4260000
0'
#4270000
b101 8
1'
#4280000
0'
#4290000
1$
1!
1.
b1010011010001010100111001000100 :
b110 8
b10 9
1'
#4300000
0'
#4310000
b1010011010100000100100101011111010000110100110001001011 :
0.
b100 9
1'
#4320000
0'
#4330000
b111 8
1'
#4340000
0'
#4350000
b1000 8
1'
#4360000
0'
#4370000
b1001 8
1'
#4380000
0'
#4390000
b1010 8
1'
#4400000
0'
#4410000
b0 #
b0 0
b0 <
b1000 >
0!
1-
b101001101001000010010010100011001010100 :
b0 8
b11 9
1'
#4420000
0'
#4430000
b1010011010100000100100101011111010000110100110001001011 :
0-
b100 9
1'
#4440000
0'
#4450000
b1 8
1'
#4460000
0'
#4470000
b10 8
1'
#4480000
0'
#4490000
b11 8
1'
#4500000
0'
#4510000
b100 8
1'
#4520000
0'
#4530000
b101 8
1'
#4540000
0'
#4550000
0$
1,
1?
1.
b1010011010001010100111001000100 :
b110 8
b10 9
1'
#4560000
0'
#4570000
b1010011010100000100100101011111010000110100110001001011 :
0.
b100 9
1'
#4580000
0'
#4590000
1"
b1000100010011110100111001000101 :
b101 9
1'
#4600000
0'
#4610000
b101001101010100010000010101001001010100 :
b0 9
1'
