Encoder_project/basic/rtl/cores/MiCalculadora/Led/bcd_siete_seg.v
/*
Modulo secuencial que convierte un nibble de 4 bits en un byte de 8 bits
para ser enviado a la pantalla 7 segmentos.

No solo se pasan números sino tambein comandos, estos se envían en el mismo formato que los números,
es decir, en 8 bits, pero con un valor diferente al de los números.
Si se quisieran modificar los comandos, se puede hacer en este modulo, ya que
es el encargado de convertir el nibble en 8 bits.
*/
module bcd_siete_seg(
    input wire[3:0] nibble,
    output reg [7:0] out_siete_seg
);
always @(*) begin
    case (nibble)
        4'h0:out_siete_seg = 8'b00111111;
        4'h1:out_siete_seg = 8'b00000110;
        4'h2:out_siete_seg = 8'b01011011; 
        4'h3:out_siete_seg = 8'b01001111;
        4'h4:out_siete_seg = 8'b01100110;
        4'h5:out_siete_seg = 8'b01101101;
        4'h6:out_siete_seg = 8'b01111101;
        4'h7:out_siete_seg = 8'b00000111;
        4'h8:out_siete_seg = 8'b01111111;
        4'h9:out_siete_seg = 8'b01101111;
        4'hA:out_siete_seg = 8'b01000000;//send_data_auto_norm_cmd
        4'hB:out_siete_seg = 8'b11000000;//set_display_Addr_0
        4'hC:out_siete_seg = 8'b10001111;//max Brightness-display ON
        default: out_siete_seg = 8'b00000000;
    endcase
end

endmodule

Encoder_project/basic/rtl/cores/MiCalculadora/Led/Com.v
module Com #(parameter divider = 20)
(
    input clk,
    input reset,
    input init,
    input [7:0]data_cmd,
    output DIO,
    output clk_com,
    output done
);

wire w_sh;
wire w_sd;
wire w_ld;
wire w_z;
wire w_clk_com_div;

clk_div #(.divider(divider)) clk_div0(.clk(clk),.reset(reset),.init(init),.z(w_z),
          .clk_com(clk_com),.clk_com_div(w_clk_com_div));

Control_Com Control0(.clk(clk),.clk_com(clk_com),.reset(reset),.init(init),.z(w_z),
                     .dn(done),.ld(w_ld),.sh(w_sh),.sd(w_sd));

data_path_Com data_path0(.clk_com_div(w_clk_com_div),.ld(w_ld),.sh(w_sh),.sd(w_sd),
                         .dn(done),.reset(reset),.data_cmd(data_cmd),.DIO(DIO),.z(w_z));
    
endmodule
/*
Este modulo se encarga de enviar un dato 8 bits a la pantalla 7 segmentos.

*/

module data_path_Com(
    input clk_com_div,
    input ld,
    input sh,
    input sd,
    input dn,
    input reset,
    input [7:0]data_cmd,
    output reg DIO,
    output reg z
);
reg [7:0]data_to_send; 
reg [3:0]sh_cnt;

always @(posedge clk_com_div or posedge reset) begin
    if (reset)begin
        data_to_send = 0;
        DIO = 0;
        sh_cnt = 0;
    end 
    else if (ld) begin
        DIO = data_cmd[0];
        data_to_send = data_cmd;
        sh_cnt = 8;
    end
    else if (sh) begin 
        data_to_send = data_to_send >> 1;
        sh_cnt = sh_cnt - 1;
    end 
    else if (sd) begin
        DIO = data_to_send[0];
    end
    else if(dn) DIO = 0;
    
end

always @(*) begin
    z = sh_cnt == 0? 1:0; 
end
    
endmodule
/*
Reloj de la pantalla 7 segementos, este modulo divide el reloj del sistema por un factor
dato por el paramatro divider, el cual es de 20 por defecto. Otra cosa a atener en cuenta
es que el no solo se genera el reloj de la pantalla sino que tambien se genera un reloj
a la mitad de la frecuencia del reloj de la pantalla, esto es necesario para el envio de datos
a la pantalla, ya que el envio de datos se hace en la mitad del periodo del reloj de la pantalla,
 es decir, cuando el reloj de la pantalla esta en 0.
 Por último es necesario ver que este reloj solo funciona cuando se esta enviando datos a la pantalla,
  es decir, cuando init = 1 o z = 0.
*/

module clk_div #(
    parameter divider = 20
) (
    input clk,
    input reset,
    input init,
    input z,
    output reg clk_com,
    output reg clk_com_div

);
reg [7:0]div_cnt;
parameter divider_2 = divider/2;

always @(posedge clk or posedge reset) begin
    if (reset)begin
        clk_com = 0;
        div_cnt = 0;
        clk_com_div = 0;
    end
    else if (init || !z || div_cnt != divider) begin
        if (div_cnt == divider)begin
            div_cnt = 0;
            clk_com = ~clk_com;
            clk_com_div = ~clk_com_div;
        end
        else if (div_cnt == divider_2) clk_com_div = ~clk_com_div;
        div_cnt = div_cnt + 1;
    end
    else begin
        div_cnt = 0;
        clk_com = 0;
        clk_com_div = 0;
    end
end 
endmodule

//MAQUINA DE CONTROL

/*
Máquina de control para la pantalla 7 segmentos 
Posible estados: START, LOAD, SHIFT, SEND
START: Estado inicial, espera a que se active la señal init para pasar al estado LOAD.
LOAD: Carga el valor de data_cmd en el registro data_to_send y pasa al estado SHIFT.
SHIFT: Desplaza el registro data_to_send 1 bit a la derecha y decrementa sh_cnt,
si sh_cnt es 0 se termina la transmisión poniendo dn = 1 y apaga la señal sd, si no pasa al estado SEND.
SEND: Activa la señal sd para enviar el bit menos significativo de data_to_send a la
pantalla, y pasa al estado SHIFT.
*/
module Control_Com(
    input       clk,
    input       clk_com,
    input       reset,
    input       init,
    input       z,

    output reg   dn,
    output reg   ld,
    output reg   sh,
    output reg   sd
);
      			
parameter START = 2'b00, LOAD = 2'b01,SHIFT = 2'b10,SEND = 2'b11;
reg [1:0] state;

always @(negedge clk or  posedge reset) begin
    if (reset) state = START;
    else begin 
        case (state)
            START:
                begin
                    if (init) state = LOAD;
                    else state = START; 
                end
            LOAD:begin
                if (clk_com) state = SHIFT;
                else state = LOAD;
            end
            SEND:begin
                if (clk_com) state = SHIFT;
                else state = SEND;
            end
            SHIFT:begin
                if (z && !clk_com) state = START;
                else if (!clk_com) state = SEND;
                else state = SHIFT;  
            end
            default:state = START;
        endcase
   end
end

always @(*) begin
    case (state)
        START: begin     
            sh = 0; ld = 0; sd = 0; dn = 1;
        end
        LOAD: begin
            sh = 0; ld = 1; sd = 0; dn = 0;
        end
        SHIFT: begin 
            sh = 1; ld = 0; sd = 0; dn = 0;
        end  
        SEND: begin
            sh = 0; ld = 0; sd = 1; dn = 0;
        end
    endcase
end
`ifdef BENCH
reg [8*40:1] state_name;
always @(*) begin
  case(state)
    START    : state_name = "START";
    LOAD     : state_name = "LOAD";
    SHIFT    : state_name = "SHIFT";
    SEND    : state_name = "SEND";
  endcase
end
`endif
endmodule

Encoder_project/basic/rtl/cores/MiCalculadora/Led/frac_bcd.v
module frac_bcd #(parameter divider = 20)
(
    input clk,
    input reset,
    input init,
    input transmision_done,
    input [31:0] in_Bcd,
    output [3:0] nibble,
    output init_send,
    output STB,
    output done
);

wire w_ld;
wire w_ld_nb;
wire w_sh;
wire w_sd;
wire w_z;
wire w_w;

data_path_frac #(.divider(divider))data_path0(.clk(clk),.reset(reset),.ld(w_ld),.ld_nb(w_ld_nb),
                     .sd(w_sd),.sh(w_sh),.in_Bcd(in_Bcd),.nibble(nibble),
                     .init_send(init_send),.STB(STB),.z(w_z),.w(w_w));

Control_frac Control0(.clk(clk),.reset(reset),.init(init),.z(w_z),.w(w_w),
                 .transmision_done(transmision_done),.dn(done),.ld(w_ld),.ld_nb(w_ld_nb),
                 .sh(w_sh),.sd(w_sd));


endmodule
/*
Este módulo se encarga de enviar los datos a la pantalla 7 segmentos de forma ordenada,
de manera que primero se envía el nibble de configuración, luego el nibble de comando y
finalmente los 8 nibbles de datos.

Es necesatio resetear la dirección de escritura de la pantalla 7 segmentos ,
 esto se hace enviando el nibble de configuración.

 Este modulo tambien se encarga de manejar el STB, el cual funciona como indicador de 
 que el dato es comando o dato, STB = 1 (COMANDO), STB = 0 (DATO). 

 El nibble que se quiere enviar no va directamente al modulo Com,sino que priemro se pasa por
 el modulo bcd_siete_seg, el cual se encarga de convertir el nibble en siete segmentos.
*/
//DATA_PATH
module data_path_frac #(parameter divider = 20)
(
    input           clk,
    input           reset,
    input           ld,
    input           ld_nb,
    input           sd,
    input           sh,

    input           [31:0]in_Bcd,
    output          reg[3:0]nibble,
    output          reg init_send,
    output          reg STB,
    output          reg z,
    output          reg w
);

reg[31:0] bcd;
reg[2:0] config_cnt;
reg[7:0] delay;
reg[4:0] sh_cnt;

always @(negedge clk or posedge reset) begin
    if (reset)begin
        bcd <= 32'h0;
        nibble <=0;
        init_send <= 0; 
        sh_cnt <= 8;
        STB <= 1;
        config_cnt <= 4;
        delay <= divider;
    end
    else begin
        if (delay) delay = delay - 1;
        else begin
            if (ld) begin
                bcd <= in_Bcd;
                config_cnt <= 4;
                sh_cnt <= 8;
                delay <= 0;
            end
            else if (ld_nb)begin

                case (config_cnt)
                    4: begin
                        nibble <= 4'hC;
                        STB <= 1;
                    end
                    3: begin
                        nibble <= 4'hA;
                        STB <= 1;
                    end
                    2: begin 
                        nibble = 4'hB;
                        STB <= 1;
                    end 
                    1: begin 
                        nibble <= bcd[31:28];
                        STB <= 0;
                    end
                    0: begin 
                        nibble <= 4'hF;
                        STB <= 0;
                    end
                    default: ;
                endcase
                delay <= divider;

            end
            else if (sd) begin 
                init_send <= 1;
                STB <= 0;
            end
            else if (sh)begin
                if (config_cnt == 0) begin 
                    bcd <= bcd << 4;
                    if (sh_cnt != 0) sh_cnt <= sh_cnt - 1;
                    config_cnt <= 1;
                end
                else config_cnt <= config_cnt - 1;
            end
            else begin
                if (sh_cnt == 0) STB <= 1'b1;
                init_send <= 1'b0;
            end
        end

    end
end
always @(*) begin
    z <= sh_cnt == 0? 1:0;
    w <= delay != 0? 1:0;
end
endmodule
//MÁQUINA DE CONTROL

/*
Este es la maquina de control que se encarga en manipular los estados del modulo data_path_frac,
de manera que se envíen los datos a la pantalla 7 segmentos de forma ordenada.
Estados posibles:
START: Estado inicial, espera a que se active la señal init para pasar al estado LOAD.
LOAD: Carga el valor de in_Bcd en el registro bcd y pasa al estado LOAD_NB.
LOAD_NB: Carga el nibble de configuración, comando o dato dependiendo del valor de config_cnt,
si config_cnt es 0 pasa al estado START, si no pasa al estado SEND.
SEND: Activa la señal init_send para enviar el nibble a la pantalla
WAIT: Espera a que transmision_done se active para pasar al estado SHIFT.
SHIFT: Desplaza el registro bcd 4 bits a la izquierda y decrementa sh_cnt,
 si sh_cnt es 0 se termina la transmisión poniendo STB = 1 y apaga la señal init_send, 
 si no pasa al estado LOAD_NB.
*/
module Control_frac(
    input       clk,
    input       reset,
    input       init,
    input       z,
    input       w,
    input       transmision_done,

    output reg   dn,
    output reg   ld,
    output reg   ld_nb,
    output reg   sh,
    output reg   sd
);
      			
parameter START = 3'b000, LOAD = 3'b001, LOAD_NB = 3'b010,SHIFT = 3'b011,
          SEND = 3'b100,WAIT = 3'b101;
reg [2:0] state;

always @(posedge clk or posedge reset) begin
    if (reset) state <= LOAD_NB;
    else begin 
        case (state)
            START:
                begin
                    if (init) state <= LOAD;
                    else state <= START; 
                end
            LOAD:state <= LOAD_NB;
            LOAD_NB:
                begin
                    if (w) state <= LOAD_NB;
                    else begin
                        if (z) state <= START;
                        else state <= SEND;
                    end
                end
            SEND:state = WAIT;
            WAIT:
                begin
                    if (transmision_done) state <= SHIFT;
                    else state <= WAIT;  
                end
            SHIFT:state <= LOAD_NB;  
            default:state <= START;
        endcase
   end
end

always @(*) begin
    if (reset)begin
        sh = 0; ld = 0; ld_nb = 0; sd = 0; dn = 1;
    end
    else begin
        case (state)
            START: begin     
                sh = 0; ld = 0; ld_nb = 0; sd = 0; dn = 1;
            end
            LOAD: begin
                sh = 0; ld = 1; ld_nb = 0; sd = 0; dn = 0;
            end
            LOAD_NB: begin
                sh = 0; ld = 0; ld_nb = 1; sd = 0; dn = 0;
            end
            SHIFT: begin 
                sh = 1; ld = 0; ld_nb = 0; sd = 0; dn = 0;
            end  
            SEND: begin
                sh = 0; ld = 0; ld_nb = 0; sd = 1; dn = 0;
            end
            WAIT: begin
                sh = 0; ld = 0; ld_nb = 0; sd = 0; dn = 0;
            end
            default:begin
                sh = 0; ld = 0; ld_nb = 0; sd = 0; dn = 0;
            end
        endcase
    end
end
`ifdef BENCH
reg [8*40:1] state_name;
always @(*) begin
  case(state)
    START    : state_name = "START";
    LOAD     : state_name = "LOAD";
    SHIFT    : state_name = "SHIFT";
    LOAD_NB    : state_name = "LOAD_NB";
    SEND    : state_name = "SEND";
    WAIT    : state_name = "WAIT";
  endcase
end
`endif
endmodule

Encoder_project/basic/rtl/cores/MiCalculadora/Led/Led.v
module Led(
    input clk,
    input reset,
    input init,
    input [31:0]in_Bcd,
    output DIO,
    output clk_com,
    output STB,
    output done
);

wire w_init_send;
wire [3:0] w_nibble;
wire [7:0] w_out_siete_seg;
wire w_transmision_done;

reg cs_operador[1:0];
reg div_done;
reg raiz_done;
reg [27:0]in_Bin;

parameter divider = 20;

   frac_bcd #(.divider(divider)) frac_bcd0(
      .clk(clk), 
      .reset(reset), 
      .init(init),
      .transmision_done(w_transmision_done), 
      .in_Bcd(in_Bcd), 
      .nibble(w_nibble),
      .init_send(w_init_send),
      .STB(STB), 
      .done(done)
   );
    Com #(.divider(divider)) Com0(
      .clk(clk), 
      .reset(reset), 
      .init(w_init_send), 
      .data_cmd(w_out_siete_seg), 
      .DIO(DIO),
      .clk_com(clk_com), 
      .done(w_transmision_done)
   );

   bcd_siete_seg bcd_siete_seg0(
      .nibble(w_nibble),
      .out_siete_seg(w_out_siete_seg));

   
    
endmodule

Encoder_project/basic/rtl/cores/MiCalculadora/Led/Led_TB.v
`timescale 1ns / 1ps
`define SIMULATION
module Led_TB;
   reg  clk;
   reg  reset;
   reg  init;
   reg  [31:0] in_Bcd;

   wire DIO;
   wire clk_com;
   wire STB;
   wire done;

   Led Led_TB(
      .clk(clk), 
      .reset(reset), 
      .init(init),
      .in_Bcd(in_Bcd), 
      .DIO(DIO),
      .clk_com(clk_com),
      .STB(STB), 
      .done(done)
   );

   parameter PERIOD = 20;
   initial begin  // Initialize Inputs
      clk = 0; reset = 0; init = 0; 
      in_Bcd = 32'h12345678;
   end
   // clk generation
   initial         clk <= 0;
   always #(PERIOD/2) clk <= ~clk;

   initial begin // Reset the system, Start the image capture process
        // Reset 
        @ (negedge clk);
	     reset = 1;
	     @ (negedge clk);
	     reset = 0;
        #(PERIOD*4)
        init = 0;
        @ (posedge clk);
        init = 1;
        #(PERIOD*2)
        init = 0;
        #(PERIOD);
   end
	 
   initial begin: TEST_CASE
     $dumpfile("Led_TB.vcd");
     $dumpvars(-1, Led_TB);
     #(PERIOD*30000) $finish;
   end

endmodule

Encoder_project/basic/rtl/cores/MiCalculadora/Led/Led_TB.vcd
$date
	Wed Jul 29 23:02:10 2026
$end
$version
	Icarus Verilog
$end
$timescale
	1ps
$end
$scope module Led_TB $end
$var wire 1 ! done $end
$var wire 1 " clk_com $end
$var wire 1 # STB $end
$var wire 1 $ DIO $end
$var reg 1 % clk $end
$var reg 32 & in_Bcd [31:0] $end
$var reg 1 ' init $end
$var reg 1 ( reset $end
$scope module Led_TB $end
$var wire 1 % clk $end
$var wire 32 ) in_Bcd [31:0] $end
$var wire 1 ' init $end
$var wire 1 ( reset $end
$var wire 1 * w_transmision_done $end
$var wire 8 + w_out_siete_seg [7:0] $end
$var wire 4 , w_nibble [3:0] $end
$var wire 1 - w_init_send $end
$var wire 1 ! done $end
$var wire 1 " clk_com $end
$var wire 1 # STB $end
$var wire 1 $ DIO $end
$scope module Com0 $end
$var wire 1 % clk $end
$var wire 1 ( reset $end
$var wire 1 . w_z $end
$var wire 1 / w_sh $end
$var wire 1 0 w_sd $end
$var wire 1 1 w_ld $end
$var wire 1 2 w_clk_com_div $end
$var wire 1 - init $end
$var wire 1 * done $end
$var wire 8 3 data_cmd [7:0] $end
$var wire 1 " clk_com $end
$var wire 1 $ DIO $end
$scope module Control0 $end
$var wire 1 % clk $end
$var wire 1 ( reset $end
$var wire 1 . z $end
$var wire 1 - init $end
$var wire 1 " clk_com $end
$var reg 1 * dn $end
$var reg 1 1 ld $end
$var reg 1 0 sd $end
$var reg 1 / sh $end
$var reg 2 4 state [1:0] $end
$var reg 320 5 state_name [320:1] $end
$upscope $end
$scope module clk_div0 $end
$var wire 1 % clk $end
$var wire 1 ( reset $end
$var wire 1 . z $end
$var wire 1 - init $end
$var reg 1 " clk_com $end
$var reg 1 2 clk_com_div $end
$var reg 8 6 div_cnt [7:0] $end
$upscope $end
$scope module data_path0 $end
$var wire 1 2 clk_com_div $end
$var wire 1 * dn $end
$var wire 1 1 ld $end
$var wire 1 ( reset $end
$var wire 1 0 sd $end
$var wire 1 / sh $end
$var wire 8 7 data_cmd [7:0] $end
$var reg 1 $ DIO $end
$var reg 8 8 data_to_send [7:0] $end
$var reg 4 9 sh_cnt [3:0] $end
$var reg 1 . z $end
$upscope $end
$upscope $end
$scope module bcd_siete_seg0 $end
$var wire 4 : nibble [3:0] $end
$var reg 8 ; out_siete_seg [7:0] $end
$upscope $end
$scope module frac_bcd0 $end
$var wire 1 % clk $end
$var wire 32 < in_Bcd [31:0] $end
$var wire 1 ' init $end
$var wire 1 ( reset $end
$var wire 1 * transmision_done $end
$var wire 1 = w_z $end
$var wire 1 > w_w $end
$var wire 1 ? w_sh $end
$var wire 1 @ w_sd $end
$var wire 1 A w_ld_nb $end
$var wire 1 B w_ld $end
$var wire 4 C nibble [3:0] $end
$var wire 1 - init_send $end
$var wire 1 ! done $end
$var wire 1 # STB $end
$scope module Control0 $end
$var wire 1 % clk $end
$var wire 1 ' init $end
$var wire 1 ( reset $end
$var wire 1 * transmision_done $end
$var wire 1 = z $end
$var wire 1 > w $end
$var reg 1 ! dn $end
$var reg 1 B ld $end
$var reg 1 A ld_nb $end
$var reg 1 @ sd $end
$var reg 1 ? sh $end
$var reg 3 D state [2:0] $end
$var reg 320 E state_name [320:1] $end
$upscope $end
$scope module data_path0 $end
$var wire 1 % clk $end
$var wire 32 F in_Bcd [31:0] $end
$var wire 1 B ld $end
$var wire 1 A ld_nb $end
$var wire 1 ( reset $end
$var wire 1 @ sd $end
$var wire 1 ? sh $end
$var reg 1 # STB $end
$var reg 32 G bcd [31:0] $end
$var reg 3 H config_cnt [2:0] $end
$var reg 8 I delay [7:0] $end
$var reg 1 - init_send $end
$var reg 4 J nibble [3:0] $end
$var reg 5 K sh_cnt [4:0] $end
$var reg 1 > w $end
$var reg 1 = z $end
$upscope $end
$upscope $end
$upscope $end
$scope begin TEST_CASE $end
$upscope $end
$upscope $end
$enddefinitions $end
#0
$dumpvars
bx K
bx J
bx I
bx H
bx G
b10010001101000101011001111000 F
bx E
bx D
bx C
0B
0A
0@
0?
x>
x=
b10010001101000101011001111000 <
bx ;
bx :
bx 9
bx 8
bx 7
bx 6
b101001101010100010000010101001001010100 5
b0 4
bx 3
x2
01
00
0/
x.
0-
bx ,
bx +
1*
b10010001101000101011001111000 )
0(
0'
b10010001101000101011001111000 &
0%
x$
x#
x"
0!
$end
#10000
b101001101010100010000010101001001010100 E
1!
b0 D
02
0"
b0 6
1%
#20000
1>
0=
b1001100010011110100000101000100010111110100111001000010 E
b111111 +
b111111 3
b111111 7
b111111 ;
b10 D
b10100 I
b100 H
1#
b1000 K
b0 ,
b0 :
b0 C
b0 J
b0 G
1.
b0 9
0$
b0 8
1(
0%
#30000
1%
#40000
0!
1A
b10011 I
0(
0%
#50000
b1 6
1%
#60000
b10010 I
0%
#70000
b10 6
1%
#80000
b10001 I
0%
#90000
b11 6
1%
#100000
b10000 I
0%
#110000
b100 6
1%
#120000
b1111 I
0%
#130000
b101 6
1'
1%
#140000
b1110 I
0%
#150000
b110 6
1%
#160000
b1101 I
0%
#170000
b111 6
1%
0'
#180000
b1100 I
0%
#190000
b1000 6
1%
#200000
b1011 I
0%
#210000
b1001 6
1%
#220000
b1010 I
0%
#230000
b1010 6
1%
#240000
b1001 I
0%
#250000
b1011 6
12
1%
#260000
b1000 I
0%
#270000
b1100 6
1%
#280000
b111 I
0%
#290000
b1101 6
1%
#300000
b110 I
0%
#310000
b1110 6
1%
#320000
b101 I
0%
#330000
b1111 6
1%
#340000
b100 I
0%
#350000
b10000 6
1%
#360000
b11 I
0%
#370000
b10001 6
1%
#380000
b10 I
0%
#390000
b10010 6
1%
#400000
b1 I
0%
#410000
b10011 6
1%
#420000
0>
b0 I
0%
#430000
b1010011010001010100111001000100 E
1@
0A
b100 D
b10100 6
1%
#440000
0#
1-
0%
#450000
b1010111010000010100100101010100 E
0@
02
1"
b1 6
b101 D
1%
#460000
0-
0*
11
b1001100010011110100000101000100 5
b1 4
0%
#470000
b10 6
1%
#480000
b101001101001000010010010100011001010100 5
01
1/
b10 4
0%
#490000
b11 6
1%
#500000
0%
#510000
b100 6
1%
#520000
0%
#530000
b101 6
1%
#540000
0%
#550000
b110 6
1%
#560000
0%
#570000
b111 6
1%
#580000
0%
#590000
b1000 6
1%
#600000
0%
#610000
b1001 6
1%
#620000
0%
#630000
b1010 6
1%
#640000
0%
#650000
0.
b1111 9
b1011 6
12
1%
#660000
0%
#670000
b1100 6
1%
#680000
0%
#690000
b1101 6
1%
#700000
0%
#710000
b1110 6
1%
#720000
0%
#730000
b1111 6
1%
#740000
0%
#750000
b10000 6
1%
#760000
0%
#770000
b10001 6
1%
#780000
0%
#790000
b10010 6
1%
#800000
0%
#810000
b10011 6
1%
#820000
0%
#830000
b10100 6
1%
#840000
0%
#850000
02
0"
b1 6
1%
#860000
10
0/
b1010011010001010100111001000100 5
b11 4
0%
#870000
b10 6
1%
#880000
0%
#890000
b11 6
1%
#900000
0%
#910000
b100 6
1%
#920000
0%
#930000
b101 6
1%
#940000
0%
#950000
b110 6
1%
#960000
0%
#970000
b111 6
1%
#980000
0%
#990000
b1000 6
1%
#1000000
0%
#1010000
b1001 6
1%
#1020000
0%
#1030000
b1010 6
1%
#1040000
0%
#1050000
b1011 6
12
1%
#1060000
0%
#1070000
b1100 6
1%
#1080000
0%
#1090000
b1101 6
1%
#1100000
0%
#1110000
b1110 6
1%
#1120000
0%
#1130000
b1111 6
1%
#1140000
0%
#1150000
b10000 6
1%
#1160000
0%
#1170000
b10001 6
1%
#1180000
0%
#1190000
b10010 6
1%
#1200000
0%
#1210000
b10011 6
1%
#1220000
0%
#1230000
b10100 6
1%
#1240000
0%
#1250000
02
1"
b1 6
1%
#1260000
b101001101001000010010010100011001010100 5
00
1/
b10 4
0%
#1270000
b10 6
1%
#1280000
0%
#1290000
b11 6
1%
#1300000
0%
#1310000
b100 6
1%
#1320000
0%
#1330000
b101 6
1%
#1340000
0%
#1350000
b110 6
1%
#1360000
0%
#1370000
b111 6
1%
#1380000
0%
#1390000
b1000 6
1%
#1400000
0%
#1410000
b1001 6
1%
#1420000
0%
#1430000
b1010 6
1%
#1440000
0%
#1450000
b1110 9
b1011 6
12
1%
#1460000
0%
#1470000
b1100 6
1%
#1480000
0%
#1490000
b1101 6
1%
#1500000
0%
#1510000
b1110 6
1%
#1520000
0%
#1530000
b1111 6
1%
#1540000
0%
#1550000
b10000 6
1%
#1560000
0%
#1570000
b10001 6
1%
#1580000
0%
#1590000
b10010 6
1%
#1600000
0%
#1610000
b10011 6
1%
#1620000
0%
#1630000
b10100 6
1%
#1640000
0%
#1650000
02
0"
b1 6
1%
#1660000
10
0/
b1010011010001010100111001000100 5
b11 4
0%
#1670000
b10 6
1%
#1680000
0%
#1690000
b11 6
1%
#1700000
0%
#1710000
b100 6
1%
#1720000
0%
#1730000
b101 6
1%
#1740000
0%
#1750000
b110 6
1%
#1760000
0%
#1770000
b111 6
1%
#1780000
0%
#1790000
b1000 6
1%
#1800000
0%
#1810000
b1001 6
1%
#1820000
0%
#1830000
b1010 6
1%
#1840000
0%
#1850000
b1011 6
12
1%
#1860000
0%
#1870000
b1100 6
1%
#1880000
0%
#1890000
b1101 6
1%
#1900000
0%
#1910000
b1110 6
1%
#1920000
0%
#1930000
b1111 6
1%
#1940000
0%
#1950000
b10000 6
1%
#1960000
0%
#1970000
b10001 6
1%
#1980000
0%
#1990000
b10010 6
1%
#2000000
0%
#2010000
b10011 6
1%
#2020000
0%
#2030000
b10100 6
1%
#2040000
0%
#2050000
02
1"
b1 6
1%
#2060000
b101001101001000010010010100011001010100 5
00
1/
b10 4
0%
#2070000
b10 6
1%
#2080000
0%
#2090000
b11 6
1%
#2100000
0%
#2110000
b100 6
1%
#2120000
0%
#2130000
b101 6
1%
#2140000
0%
#2150000
b110 6
1%
#2160000
0%
#2170000
b111 6
1%
#2180000
0%
#2190000
b1000 6
1%
#2200000
0%
#2210000
b1001 6
1%
#2220000
0%
#2230000
b1010 6
1%
#2240000
0%
#2250000
b1101 9
b1011 6
12
1%
#2260000
0%
#2270000
b1100 6
1%
#2280000
0%
#2290000
b1101 6
1%
#2300000
0%
#2310000
b1110 6
1%
#2320000
0%
#2330000
b1111 6
1%
#2340000
0%
#2350000
b10000 6
1%
#2360000
0%
#2370000
b10001 6
1%
#2380000
0%
#2390000
b10010 6
1%
#2400000
0%
#2410000
b10011 6
1%
#2420000
0%
#2430000
b10100 6
1%
#2440000
0%
#2450000
02
0"
b1 6
1%
#2460000
10
0/
b1010011010001010100111001000100 5
b11 4
0%
#2470000
b10 6
1%
#2480000
0%
#2490000
b11 6
1%
#2500000
0%
#2510000
b100 6
1%
#2520000
0%
#2530000
b101 6
1%
#2540000
0%
#2550000
b110 6
1%
#2560000
0%
#2570000
b111 6
1%
#2580000
0%
#2590000
b1000 6
1%
#2600000
0%
#2610000
b1001 6
1%
#2620000
0%
#2630000
b1010 6
1%
#2640000
0%
#2650000
b1011 6
12
1%
#2660000
0%
#2670000
b1100 6
1%
#2680000
0%
#2690000
b1101 6
1%
#2700000
0%
#2710000
b1110 6
1%
#2720000
0%
#2730000
b1111 6
1%
#2740000
0%
#2750000
b10000 6
1%
#2760000
0%
#2770000
b10001 6
1%
#2780000
0%
#2790000
b10010 6
1%
#2800000
0%
#2810000
b10011 6
1%
#2820000
0%
#2830000
b10100 6
1%
#2840000
0%
#2850000
02
1"
b1 6
1%
#2860000
b101001101001000010010010100011001010100 5
00
1/
b10 4
0%
#2870000
b10 6
1%
#2880000
0%
#2890000
b11 6
1%
#2900000
0%
#2910000
b100 6
1%
#2920000
0%
#2930000
b101 6
1%
#2940000
0%
#2950000
b110 6
1%
#2960000
0%
#2970000
b111 6
1%
#2980000
0%
#2990000
b1000 6
1%
#3000000
0%
#3010000
b1001 6
1%
#3020000
0%
#3030000
b1010 6
1%
#3040000
0%
#3050000
b1100 9
b1011 6
12
1%
#3060000
0%
#3070000
b1100 6
1%
#3080000
0%
#3090000
b1101 6
1%
#3100000
0%
#3110000
b1110 6
1%
#3120000
0%
#3130000
b1111 6
1%
#3140000
0%
#3150000
b10000 6
1%
#3160000
0%
#3170000
b10001 6
1%
#3180000
0%
#3190000
b10010 6
1%
#3200000
0%
#3210000
b10011 6
1%
#3220000
0%
#3230000
b10100 6
1%
#3240000
0%
#3250000
02
0"
b1 6
1%
#3260000
10
0/
b1010011010001010100111001000100 5
b11 4
0%
#3270000
b10 6
1%
#3280000
0%
#3290000
b11 6
1%
#3300000
0%
#3310000
b100 6
1%
#3320000
0%
#3330000
b101 6
1%
#3340000
0%
#3350000
b110 6
1%
#3360000
0%
#3370000
b111 6
1%
#3380000
0%
#3390000
b1000 6
1%
#3400000
0%
#3410000
b1001 6
1%
#3420000
0%
#3430000
b1010 6
1%
#3440000
0%
#3450000
b1011 6
12
1%
#3460000
0%
#3470000
b1100 6
1%
#3480000
0%
#3490000
b1101 6
1%
#3500000
0%
#3510000
b1110 6
1%
#3520000
0%
#3530000
b1111 6
1%
#3540000
0%
#3550000
b10000 6
1%
#3560000
0%
#3570000
b10001 6
1%
#3580000
0%
#3590000
b10010 6
1%
#3600000
0%
#3610000
b10011 6
1%
#3620000
0%
#3630000
b10100 6
1%
#3640000
0%
#3650000
02
1"
b1 6
1%
#3660000
b101001101001000010010010100011001010100 5
00
1/
b10 4
0%
#3670000
b10 6
1%
#3680000
0%
#3690000
b11 6
1%
#3700000
0%
#3710000
b100 6
1%
#3720000
0%
#3730000
b101 6
1%
#3740000
0%
#3750000
b110 6
1%
#3760000
0%
#3770000
b111 6
1%
#3780000
0%
#3790000
b1000 6
1%
#3800000
0%
#3810000
b1001 6
1%
#3820000
0%
#3830000
b1010 6
1%
#3840000
0%
#3850000
b1011 9
b1011 6
12
1%
#3860000
0%
#3870000
b1100 6
1%
#3880000
0%
#3890000
b1101 6
1%
#3900000
0%
#3910000
b1110 6
1%
#3920000
0%
#3930000
b1111 6
1%
#3940000
0%
#3950000
b10000 6
1%
#3960000
0%
#3970000
b10001 6
1%
#3980000
0%
#3990000
b10010 6
1%
#4000000
0%
#4010000
b10011 6
1%
#4020000
0%
#4030000
b10100 6
1%
#4040000
0%
#4050000
02
0"
b1 6
1%
#4060000
10
0/
b1010011010001010100111001000100 5
b11 4
0%
#4070000
b10 6
1%
#4080000
0%
#4090000
b11 6
1%
#4100000
0%
#4110000
b100 6
1%
#4120000
0%
#4130000
b101 6
1%
#4140000
0%
#4150000
b110 6
1%
#4160000
0%
#4170000
b111 6
1%
#4180000
0%
#4190000
b1000 6
1%
#4200000
0%
#4210000
b1001 6
1%
#4220000
0%
#4230000
b1010 6
1%
#4240000
0%
#4250000
b1011 6
12
1%
#4260000
0%
#4270000
b1100 6
1%
#4280000
0%
#4290000
b1101 6
1%
#4300000
0%
#4310000
b1110 6
1%
#4320000
0%
#4330000
b1111 6
1%
#4340000
0%
#4350000
b10000 6
1%
#4360000
0%
#4370000
b10001 6
1%
#4380000
0%
#4390000
b10010 6
1%
#4400000
0%
#4410000
b10011 6
1%
#4420000
0%
#4430000
b10100 6
1%
#4440000
0%
#4450000
02
1"
b1 6
1%
#4460000
b101001101001000010010010100011001010100 5
00
1/
b10 4
0%
#4470000
b10 6
1%
#4480000
0%
#4490000
b11 6
1%
#4500000
0%
#4510000
b100 6
1%
#4520000
0%
#4530000
b101 6
1%
#4540000
0%
#4550000
b110 6
1%
#4560000
0%
#4570000
b111 6
1%
#4580000
0%
#4590000
b1000 6
1%
#4600000
0%
#4610000
b1001 6
1%
#4620000
0%
#4630000
b1010 6
1%
#4640000
0%
